orbitdb_kit/__init__.py
orbitdb_kit/orbitdb_kit.py
orbitdb_kit/orbitdb_kit_lib.py
orbitdb_kit/orbitv3-slave-swarm.js
orbitdb_kit/package.json
orbitdb_kit/websocket_kit.py
orbitdb_kit/websocket_kit_lib.py
orbitdb_kit/yarn.lock
orbitdb_kit-0.0.4.dist-info/LICENSE
orbitdb_kit-0.0.4.dist-info/METADATA
orbitdb_kit-0.0.4.dist-info/WHEEL
orbitdb_kit-0.0.4.dist-info/top_level.txt
orbitdb_kit-0.0.4.dist-info/RECORD
